README.md
setup.py
sopn_publish_date/__init__.py
sopn_publish_date/bank-holidays.json
sopn_publish_date/calendars.py
sopn_publish_date/date.py
sopn_publish_date/election_ids.py
sopn_publish_date.egg-info/PKG-INFO
sopn_publish_date.egg-info/SOURCES.txt
sopn_publish_date.egg-info/dependency_links.txt
sopn_publish_date.egg-info/top_level.txt