Metadata-Version: 2.1
Name: sopn-publish-date
Version: 1.4.3
Summary: Derive publish dates of Statements of Persons Nominated for UK elections
Home-page: https://github.com/mrwilson/sopn-publish-date
Author: Alex Wilson
Author-email: alex+github@probablyfine.co.uk
License: MIT
Platform: UNKNOWN
Classifier: License :: OSI Approved :: MIT License
Classifier: Topic :: Software Development
Classifier: Topic :: Software Development :: Documentation
